alidadataset/__init__.py
alidadataset/dataset.py
alidadataset/model.py
alidadataset/utils.py
alidadataset/serializations/__init__.py
alidadataset/serializations/_datasets_dataset_dict_datasetdict.py
alidadataset/serializations/_pandas_core_frame_dataframe.py
alidadataset/serializations/hugging_face_dataset.py
alidadataset/serializations/hugging_face_from_csv.py
alidadataset/serializations/kafka_channel.py
alidadataset/serializations/pandas_dataframe.py
alidadataset/serializations/path.py
alidadataset/serializations/streaming_input.py
alidadataset/serializations/streaming_output.py
alida_dataset-0.0.14.dist-info/METADATA
alida_dataset-0.0.14.dist-info/WHEEL
alida_dataset-0.0.14.dist-info/top_level.txt
alida_dataset-0.0.14.dist-info/RECORD
